CHANGES.txt
LICENSE.txt
MANIFEST.in
README.txt
TODO.txt
buildout.cfg
setup.py
eggs/BTrees-4.11.2-py3.10-win-amd64.egg/EGG-INFO/LICENSE.txt
eggs/BTrees-4.11.2-py3.10-win-amd64.egg/EGG-INFO/requires.txt
eggs/BTrees-4.11.2-py3.10-win-amd64.egg/EGG-INFO/top_level.txt
eggs/WSGIProxy2-0.5.1-py3.10.egg/EGG-INFO/entry_points.txt
eggs/WSGIProxy2-0.5.1-py3.10.egg/EGG-INFO/requires.txt
eggs/WSGIProxy2-0.5.1-py3.10.egg/EGG-INFO/top_level.txt
eggs/WebOb-1.8.7-py3.10.egg/EGG-INFO/license.txt
eggs/WebOb-1.8.7-py3.10.egg/EGG-INFO/requires.txt
eggs/WebOb-1.8.7-py3.10.egg/EGG-INFO/top_level.txt
eggs/WebTest-2.0.35-py3.10.egg/EGG-INFO/entry_points.txt
eggs/WebTest-2.0.35-py3.10.egg/EGG-INFO/requires.txt
eggs/WebTest-2.0.35-py3.10.egg/EGG-INFO/top_level.txt
eggs/ZConfig-3.6.1-py3.10.egg/EGG-INFO/LICENSE.txt
eggs/ZConfig-3.6.1-py3.10.egg/EGG-INFO/entry_points.txt
eggs/ZConfig-3.6.1-py3.10.egg/EGG-INFO/requires.txt
eggs/ZConfig-3.6.1-py3.10.egg/EGG-INFO/top_level.txt
eggs/ZConfig-3.6.1-py3.10.egg/ZConfig/schemaless.txt
eggs/ZConfig-3.6.1-py3.10.egg/ZConfig/tests/input/non-ascii.txt
eggs/ZConfig-3.6.1-py3.10.egg/ZConfig/tests/library/README.txt
eggs/ZConfig-3.6.1-py3.10.egg/ZConfig/tests/zipsource/README.txt
eggs/beautifulsoup4-4.9.3-py3.10.egg/EGG-INFO/COPYING.txt
eggs/beautifulsoup4-4.9.3-py3.10.egg/EGG-INFO/requires.txt
eggs/beautifulsoup4-4.9.3-py3.10.egg/EGG-INFO/top_level.txt
eggs/cffi-2.0.0-py3.10-win-amd64.egg/EGG-INFO/entry_points.txt
eggs/cffi-2.0.0-py3.10-win-amd64.egg/EGG-INFO/requires.txt
eggs/cffi-2.0.0-py3.10-win-amd64.egg/EGG-INFO/top_level.txt
eggs/future-1.0.0-py3.10.egg/EGG-INFO/LICENSE.txt
eggs/future-1.0.0-py3.10.egg/EGG-INFO/entry_points.txt
eggs/future-1.0.0-py3.10.egg/EGG-INFO/top_level.txt
eggs/j01.dialog-3.0.2-py3.10.egg/EGG-INFO/SOURCES.txt
eggs/j01.dialog-3.0.2-py3.10.egg/EGG-INFO/dependency_links.txt
eggs/j01.dialog-3.0.2-py3.10.egg/EGG-INFO/namespace_packages.txt
eggs/j01.dialog-3.0.2-py3.10.egg/EGG-INFO/requires.txt
eggs/j01.dialog-3.0.2-py3.10.egg/EGG-INFO/top_level.txt
eggs/j01.dialog-3.0.2-py3.10.egg/j01/dialog/README.txt
eggs/j01.dialog-3.0.2-py3.10.egg/j01/dialog/checker.txt
eggs/j01.jsonrpc-3.0.2-py3.10.egg/EGG-INFO/SOURCES.txt
eggs/j01.jsonrpc-3.0.2-py3.10.egg/EGG-INFO/dependency_links.txt
eggs/j01.jsonrpc-3.0.2-py3.10.egg/EGG-INFO/namespace_packages.txt
eggs/j01.jsonrpc-3.0.2-py3.10.egg/EGG-INFO/requires.txt
eggs/j01.jsonrpc-3.0.2-py3.10.egg/EGG-INFO/top_level.txt
eggs/j01.jsonrpc-3.0.2-py3.10.egg/j01/jsonrpc/README.txt
eggs/j01.jsonrpc-3.0.2-py3.10.egg/j01/jsonrpc/checker.txt
eggs/j01.jsonrpc-3.0.2-py3.10.egg/j01/jsonrpc/js/README.txt
eggs/lxml-6.0.2-py3.10-win-amd64.egg/EGG-INFO/requires.txt
eggs/lxml-6.0.2-py3.10-win-amd64.egg/EGG-INFO/top_level.txt
eggs/lxml-6.0.2-py3.10-win-amd64.egg/EGG-INFO/licenses/LICENSE.txt
eggs/lxml-6.0.2-py3.10-win-amd64.egg/EGG-INFO/licenses/LICENSES.txt
eggs/lxml-6.0.2-py3.10-win-amd64.egg/lxml/isoschematron/resources/xsl/iso-schematron-xslt1/readme.txt
eggs/multipart-1.3.0-py3.10.egg/EGG-INFO/requires.txt
eggs/p01.checker-0.5.16-py3.10.egg/EGG-INFO/SOURCES.txt
eggs/p01.checker-0.5.16-py3.10.egg/EGG-INFO/dependency_links.txt
eggs/p01.checker-0.5.16-py3.10.egg/EGG-INFO/namespace_packages.txt
eggs/p01.checker-0.5.16-py3.10.egg/EGG-INFO/requires.txt
eggs/p01.checker-0.5.16-py3.10.egg/EGG-INFO/top_level.txt
eggs/p01.checker-0.5.16-py3.10.egg/p01/checker/checker.txt
eggs/p01.checker-0.5.16-py3.10.egg/p01/checker/sample/tab.txt
eggs/p01.json-0.7.2-py3.10.egg/EGG-INFO/SOURCES.txt
eggs/p01.json-0.7.2-py3.10.egg/EGG-INFO/dependency_links.txt
eggs/p01.json-0.7.2-py3.10.egg/EGG-INFO/namespace_packages.txt
eggs/p01.json-0.7.2-py3.10.egg/EGG-INFO/requires.txt
eggs/p01.json-0.7.2-py3.10.egg/EGG-INFO/top_level.txt
eggs/p01.json-0.7.2-py3.10.egg/p01/json/README.txt
eggs/p01.jsonrpc-0.8.1-py3.10.egg/EGG-INFO/SOURCES.txt
eggs/p01.jsonrpc-0.8.1-py3.10.egg/EGG-INFO/dependency_links.txt
eggs/p01.jsonrpc-0.8.1-py3.10.egg/EGG-INFO/namespace_packages.txt
eggs/p01.jsonrpc-0.8.1-py3.10.egg/EGG-INFO/requires.txt
eggs/p01.jsonrpc-0.8.1-py3.10.egg/EGG-INFO/top_level.txt
eggs/p01.jsonrpc-0.8.1-py3.10.egg/p01/jsonrpc/README.txt
eggs/p01.jsonrpc-0.8.1-py3.10.egg/p01/jsonrpc/zcml.txt
eggs/p01.recipe.setup-0.8.19-py3.10.egg/EGG-INFO/SOURCES.txt
eggs/p01.recipe.setup-0.8.19-py3.10.egg/EGG-INFO/dependency_links.txt
eggs/p01.recipe.setup-0.8.19-py3.10.egg/EGG-INFO/entry_points.txt
eggs/p01.recipe.setup-0.8.19-py3.10.egg/EGG-INFO/namespace_packages.txt
eggs/p01.recipe.setup-0.8.19-py3.10.egg/EGG-INFO/requires.txt
eggs/p01.recipe.setup-0.8.19-py3.10.egg/EGG-INFO/top_level.txt
eggs/p01.recipe.setup-0.8.19-py3.10.egg/p01/recipe/setup/README.txt
eggs/p01.recipe.setup-0.8.19-py3.10.egg/p01/recipe/setup/checker.txt
eggs/p01.recipe.setup-0.8.19-py3.10.egg/p01/recipe/setup/cmd.txt
eggs/p01.recipe.setup-0.8.19-py3.10.egg/p01/recipe/setup/copy.txt
eggs/p01.recipe.setup-0.8.19-py3.10.egg/p01/recipe/setup/download.txt
eggs/p01.recipe.setup-0.8.19-py3.10.egg/p01/recipe/setup/fetch.txt
eggs/p01.recipe.setup-0.8.19-py3.10.egg/p01/recipe/setup/i18n.txt
eggs/p01.recipe.setup-0.8.19-py3.10.egg/p01/recipe/setup/importchecker.txt
eggs/p01.recipe.setup-0.8.19-py3.10.egg/p01/recipe/setup/index.txt
eggs/p01.recipe.setup-0.8.19-py3.10.egg/p01/recipe/setup/mkdir.txt
eggs/p01.recipe.setup-0.8.19-py3.10.egg/p01/recipe/setup/mkfile.txt
eggs/p01.recipe.setup-0.8.19-py3.10.egg/p01/recipe/setup/paste.txt
eggs/p01.recipe.setup-0.8.19-py3.10.egg/p01/recipe/setup/script.txt
eggs/p01.recipe.setup-0.8.19-py3.10.egg/p01/recipe/setup/scripts.txt
eggs/p01.schema-0.5.0-py3.10.egg/EGG-INFO/SOURCES.txt
eggs/p01.schema-0.5.0-py3.10.egg/EGG-INFO/dependency_links.txt
eggs/p01.schema-0.5.0-py3.10.egg/EGG-INFO/namespace_packages.txt
eggs/p01.schema-0.5.0-py3.10.egg/EGG-INFO/requires.txt
eggs/p01.schema-0.5.0-py3.10.egg/EGG-INFO/top_level.txt
eggs/p01.testbrowser-3.0.0-py3.10.egg/EGG-INFO/SOURCES.txt
eggs/p01.testbrowser-3.0.0-py3.10.egg/EGG-INFO/dependency_links.txt
