Metadata-Version: 2.1
Name: j01.form
Version: 4.0.7
Summary: Enhanced zope 3 form with jsonrpc, history and a lot more
Home-page: https://pypi.org/project/j01.form/
Author: Roger Ineichen, Projekt01 GmbH
Author-email: dev@projekt01.ch
License: ZPL 2.1
Keywords: j01 p01 z3c form twitter bootstrap 3 jquery Zope3
Platform: UNKNOWN
Classifier: Development Status :: 5 - Production/Stable
Classifier: Environment :: Web Environment
Classifier: Intended Audience :: Developers
Classifier: License :: OSI Approved :: Zope Public License
Classifier: Programming Language :: Python
Classifier: Natural Language :: English
Classifier: Operating System :: OS Independent
Classifier: Topic :: Internet :: WWW/HTTP
Classifier: Framework :: Zope3
Provides-Extra: test
